jsonschemanlplab/__init__.py
jsonschemanlplab/__main__.py
jsonschemanlplab/_format.py
jsonschemanlplab/_legacy_validators.py
jsonschemanlplab/_reflect.py
jsonschemanlplab/_types.py
jsonschemanlplab/_utils.py
jsonschemanlplab/_validators.py
jsonschemanlplab/cli.py
jsonschemanlplab/compat.py
jsonschemanlplab/exceptions.py
jsonschemanlplab/validators.py
jsonschemanlplab/benchmarks/__init__.py
jsonschemanlplab/benchmarks/issue232.py
jsonschemanlplab/benchmarks/json_schema_test_suite.py
jsonschemanlplab/schemas/draft3.json
jsonschemanlplab/schemas/draft4.json
jsonschemanlplab/schemas/draft6.json
jsonschemanlplab/schemas/draft7.json
jsonschemanlplab/tests/__init__.py
jsonschemanlplab/tests/_suite.py
jsonschemanlplab/tests/test_cli.py
jsonschemanlplab/tests/test_exceptions.py
jsonschemanlplab/tests/test_format.py
jsonschemanlplab/tests/test_jsonschema_test_suite.py
jsonschemanlplab/tests/test_types.py
jsonschemanlplab/tests/test_validators.py
jsonschemanlplab-3.0.1.1.dist-info/COPYING
jsonschemanlplab-3.0.1.1.dist-info/METADATA
jsonschemanlplab-3.0.1.1.dist-info/WHEEL
jsonschemanlplab-3.0.1.1.dist-info/entry_points.txt
jsonschemanlplab-3.0.1.1.dist-info/top_level.txt
jsonschemanlplab-3.0.1.1.dist-info/RECORD
