Metadata-Version: 2.1
Name: jsonschemanlplab
Version: 3.0.1.1
Summary: An implementation of JSON Schema validation for Python, forked to avoid dependency issues
Home-page: https://github.com/orenbaldinger/jsonschema-nlplab
Author: Oren Baldinger
Author-email: oren@baldinger.me
License: UNKNOWN
Project-URL: Docs, https://python-jsonschema.readthedocs.io/en/latest/
Platform: UNKNOWN
Classifier: Development Status :: 5 - Production/Stable
Classifier: Intended Audience :: Developers
Classifier: License :: OSI Approved :: MIT License
Classifier: Operating System :: OS Independent
Classifier: Programming Language :: Python
Classifier: Programming Language :: Python :: 2
Classifier: Programming Language :: Python :: 2.7
Classifier: Programming Language :: Python :: 3
Classifier: Programming Language :: Python :: 3.5
Classifier: Programming Language :: Python :: 3.6
Classifier: Programming Language :: Python :: 3.7
Classifier: Programming Language :: Python :: Implementation :: CPython
Classifier: Programming Language :: Python :: Implementation :: PyPy
Requires-Dist: attrs (>=17.4.0)
Requires-Dist: pyrsistent (>=0.14.0)
Requires-Dist: setuptools
Requires-Dist: six (>=1.11.0)
Requires-Dist: functools32 ; python_version < "3"
Provides-Extra: format
Requires-Dist: idna ; extra == 'format'
Requires-Dist: jsonpointer (>1.13) ; extra == 'format'
Requires-Dist: rfc3987 ; extra == 'format'
Requires-Dist: strict-rfc3339 ; extra == 'format'
Requires-Dist: webcolors ; extra == 'format'
